{
	"$schema": "http://schema.management.azure.com/schemas/2015-01-01/deploymentTemplate.json#",
	"contentVersion": "1.0.0.0",
	"parameters": {
		"factoryName": {
			"type": "string",
			"metadata": "Nom de fabrique de données",
			"defaultValue": "datafactoryrime"
		},
		"AzureDataLakeStorage1_accountKey": {
			"type": "secureString",
			"metadata": "Chaîne sécurisée pour « accountKey » de « AzureDataLakeStorage1 »"
		},
		"FileServer1_password": {
			"type": "secureString",
			"metadata": "Chaîne sécurisée pour « password » de « FileServer1 »"
		},
		"AzureDataLakeStorage1_properties_typeProperties_url": {
			"type": "string",
			"defaultValue": "https://formationrime.dfs.core.windows.net/"
		},
		"FileServer1_properties_typeProperties_host": {
			"type": "string",
			"defaultValue": "C:\\Users\\rokacha\\Desktop\\azure"
		},
		"FileServer1_properties_typeProperties_userId": {
			"type": "string",
			"defaultValue": "BETD\\rokacha"
		}
	},
	"variables": {
		"factoryId": "[concat('Microsoft.DataFactory/factories/', parameters('factoryName'))]"
	},
	"resources": [
		{
			"name": "[concat(parameters('factoryName'), '/AzureDataLakeStorage1')]",
			"type": "Microsoft.DataFactory/factories/linkedServices",
			"apiVersion": "2018-06-01",
			"properties": {
				"annotations": [],
				"type": "AzureBlobFS",
				"typeProperties": {
					"url": "[parameters('AzureDataLakeStorage1_properties_typeProperties_url')]",
					"accountKey": {
						"type": "SecureString",
						"value": "[parameters('AzureDataLakeStorage1_accountKey')]"
					}
				}
			},
			"dependsOn": []
		},
		{
			"name": "[concat(parameters('factoryName'), '/integrationRuntime1')]",
			"type": "Microsoft.DataFactory/factories/integrationRuntimes",
			"apiVersion": "2018-06-01",
			"properties": {
				"type": "SelfHosted",
				"typeProperties": {}
			},
			"dependsOn": []
		},
		{
			"name": "[concat(parameters('factoryName'), '/Tar1')]",
			"type": "Microsoft.DataFactory/factories/datasets",
			"apiVersion": "2018-06-01",
			"properties": {
				"linkedServiceName": {
					"referenceName": "AzureDataLakeStorage1",
					"type": "LinkedServiceReference"
				},
				"annotations": [],
				"type": "DelimitedText",
				"typeProperties": {
					"location": {
						"type": "AzureBlobFSLocation",
						"fileSystem": "rawdata"
					},
					"columnDelimiter": ",",
					"escapeChar": "\\",
					"firstRowAsHeader": true,
					"quoteChar": "\""
				},
				"schema": []
			},
			"dependsOn": [
				"[concat(variables('factoryId'), '/linkedServices/AzureDataLakeStorage1')]"
			]
		},
		{
			"name": "[concat(parameters('factoryName'), '/Tar2')]",
			"type": "Microsoft.DataFactory/factories/datasets",
			"apiVersion": "2018-06-01",
			"properties": {
				"linkedServiceName": {
					"referenceName": "AzureDataLakeStorage1",
					"type": "LinkedServiceReference"
				},
				"annotations": [],
				"type": "DelimitedText",
				"typeProperties": {
					"location": {
						"type": "AzureBlobFSLocation",
						"fileSystem": "rawdata"
					},
					"columnDelimiter": ",",
					"escapeChar": "\\",
					"firstRowAsHeader": true,
					"quoteChar": "\""
				},
				"schema": []
			},
			"dependsOn": [
				"[concat(variables('factoryId'), '/linkedServices/AzureDataLakeStorage1')]"
			]
		},
		{
			"name": "[concat(parameters('factoryName'), '/Tar3')]",
			"type": "Microsoft.DataFactory/factories/datasets",
			"apiVersion": "2018-06-01",
			"properties": {
				"linkedServiceName": {
					"referenceName": "AzureDataLakeStorage1",
					"type": "LinkedServiceReference"
				},
				"annotations": [],
				"type": "DelimitedText",
				"typeProperties": {
					"location": {
						"type": "AzureBlobFSLocation",
						"fileSystem": "rawdata"
					},
					"columnDelimiter": ",",
					"escapeChar": "\\",
					"firstRowAsHeader": true,
					"quoteChar": "\""
				},
				"schema": []
			},
			"dependsOn": [
				"[concat(variables('factoryId'), '/linkedServices/AzureDataLakeStorage1')]"
			]
		},
		{
			"name": "[concat(parameters('factoryName'), '/Tarcsv1')]",
			"type": "Microsoft.DataFactory/factories/datasets",
			"apiVersion": "2018-06-01",
			"properties": {
				"linkedServiceName": {
					"referenceName": "AzureDataLakeStorage1",
					"type": "LinkedServiceReference"
				},
				"annotations": [],
				"type": "DelimitedText",
				"typeProperties": {
					"location": {
						"type": "AzureBlobFSLocation",
						"fileName": "data-1.csv",
						"fileSystem": "rawdata"
					},
					"columnDelimiter": ",",
					"escapeChar": "\\",
					"firstRowAsHeader": true,
					"quoteChar": "\""
				},
				"schema": []
			},
			"dependsOn": [
				"[concat(variables('factoryId'), '/linkedServices/AzureDataLakeStorage1')]"
			]
		},
		{
			"name": "[concat(parameters('factoryName'), '/Tarcsv2')]",
			"type": "Microsoft.DataFactory/factories/datasets",
			"apiVersion": "2018-06-01",
			"properties": {
				"linkedServiceName": {
					"referenceName": "AzureDataLakeStorage1",
					"type": "LinkedServiceReference"
				},
				"annotations": [],
				"type": "DelimitedText",
				"typeProperties": {
					"location": {
						"type": "AzureBlobFSLocation",
						"fileName": "data-2.csv",
						"fileSystem": "rawdata"
					},
					"columnDelimiter": ",",
					"escapeChar": "\\",
					"firstRowAsHeader": true,
					"quoteChar": "\""
				},
				"schema": []
			},
			"dependsOn": [
				"[concat(variables('factoryId'), '/linkedServices/AzureDataLakeStorage1')]"
			]
		},
		{
			"name": "[concat(parameters('factoryName'), '/Tarcsv3')]",
			"type": "Microsoft.DataFactory/factories/datasets",
			"apiVersion": "2018-06-01",
			"properties": {
				"linkedServiceName": {
					"referenceName": "AzureDataLakeStorage1",
					"type": "LinkedServiceReference"
				},
				"annotations": [],
				"type": "DelimitedText",
				"typeProperties": {
					"location": {
						"type": "AzureBlobFSLocation",
						"fileName": "data-3.csv",
						"fileSystem": "rawdata"
					},
					"columnDelimiter": ",",
					"escapeChar": "\\",
					"firstRowAsHeader": true,
					"quoteChar": "\""
				},
				"schema": []
			},
			"dependsOn": [
				"[concat(variables('factoryId'), '/linkedServices/AzureDataLakeStorage1')]"
			]
		},
		{
			"name": "[concat(parameters('factoryName'), '/Tarcsv4')]",
			"type": "Microsoft.DataFactory/factories/datasets",
			"apiVersion": "2018-06-01",
			"properties": {
				"linkedServiceName": {
					"referenceName": "AzureDataLakeStorage1",
					"type": "LinkedServiceReference"
				},
				"annotations": [],
				"type": "DelimitedText",
				"typeProperties": {
					"location": {
						"type": "AzureBlobFSLocation",
						"fileName": "data-4.csv",
						"fileSystem": "rawdata"
					},
					"columnDelimiter": ",",
					"escapeChar": "\\",
					"firstRowAsHeader": true,
					"quoteChar": "\""
				},
				"schema": []
			},
			"dependsOn": [
				"[concat(variables('factoryId'), '/linkedServices/AzureDataLakeStorage1')]"
			]
		},
		{
			"name": "[concat(parameters('factoryName'), '/Tarcsv5')]",
			"type": "Microsoft.DataFactory/factories/datasets",
			"apiVersion": "2018-06-01",
			"properties": {
				"linkedServiceName": {
					"referenceName": "AzureDataLakeStorage1",
					"type": "LinkedServiceReference"
				},
				"annotations": [],
				"type": "DelimitedText",
				"typeProperties": {
					"location": {
						"type": "AzureBlobFSLocation",
						"fileName": "data-5.csv",
						"fileSystem": "rawdata"
					},
					"columnDelimiter": ",",
					"escapeChar": "\\",
					"firstRowAsHeader": true,
					"quoteChar": "\""
				},
				"schema": []
			},
			"dependsOn": [
				"[concat(variables('factoryId'), '/linkedServices/AzureDataLakeStorage1')]"
			]
		},
		{
			"name": "[concat(parameters('factoryName'), '/Tarcsv6')]",
			"type": "Microsoft.DataFactory/factories/datasets",
			"apiVersion": "2018-06-01",
			"properties": {
				"linkedServiceName": {
					"referenceName": "AzureDataLakeStorage1",
					"type": "LinkedServiceReference"
				},
				"annotations": [],
				"type": "DelimitedText",
				"typeProperties": {
					"location": {
						"type": "AzureBlobFSLocation",
						"fileName": "data-6.csv",
						"fileSystem": "rawdata"
					},
					"columnDelimiter": ",",
					"escapeChar": "\\",
					"firstRowAsHeader": true,
					"quoteChar": "\""
				},
				"schema": []
			},
			"dependsOn": [
				"[concat(variables('factoryId'), '/linkedServices/AzureDataLakeStorage1')]"
			]
		},
		{
			"name": "[concat(parameters('factoryName'), '/FileServer1')]",
			"type": "Microsoft.DataFactory/factories/linkedServices",
			"apiVersion": "2018-06-01",
			"properties": {
				"annotations": [],
				"type": "FileServer",
				"typeProperties": {
					"host": "[parameters('FileServer1_properties_typeProperties_host')]",
					"userId": "[parameters('FileServer1_properties_typeProperties_userId')]",
					"password": {
						"type": "SecureString",
						"value": "[parameters('FileServer1_password')]"
					}
				},
				"connectVia": {
					"referenceName": "integrationRuntime1",
					"type": "IntegrationRuntimeReference"
				}
			},
			"dependsOn": [
				"[concat(variables('factoryId'), '/integrationRuntimes/integrationRuntime1')]"
			]
		},
		{
			"name": "[concat(parameters('factoryName'), '/Src1')]",
			"type": "Microsoft.DataFactory/factories/datasets",
			"apiVersion": "2018-06-01",
			"properties": {
				"linkedServiceName": {
					"referenceName": "FileServer1",
					"type": "LinkedServiceReference"
				},
				"annotations": [],
				"type": "DelimitedText",
				"typeProperties": {
					"location": {
						"type": "FileServerLocation",
						"fileName": "sg-metro-opendata-2021-03-18-17h22.csv"
					},
					"columnDelimiter": ",",
					"escapeChar": "\\",
					"firstRowAsHeader": true,
					"quoteChar": "\""
				},
				"schema": [
					{
						"name": "epci2020",
						"type": "String"
					},
					{
						"name": "semaine_glissante",
						"type": "String"
					},
					{
						"name": "clage_65",
						"type": "String"
					},
					{
						"name": "ti",
						"type": "String"
					}
				]
			},
			"dependsOn": [
				"[concat(variables('factoryId'), '/linkedServices/FileServer1')]"
			]
		},
		{
			"name": "[concat(parameters('factoryName'), '/Src2')]",
			"type": "Microsoft.DataFactory/factories/datasets",
			"apiVersion": "2018-06-01",
			"properties": {
				"linkedServiceName": {
					"referenceName": "FileServer1",
					"type": "LinkedServiceReference"
				},
				"annotations": [],
				"type": "DelimitedText",
				"typeProperties": {
					"location": {
						"type": "FileServerLocation",
						"fileName": "sites-prelevements-grand-public.csv"
					},
					"columnDelimiter": ",",
					"escapeChar": "\\",
					"firstRowAsHeader": true,
					"quoteChar": "\""
				},
				"schema": [
					{
						"name": "ID",
						"type": "String"
					},
					{
						"name": "id_ej",
						"type": "String"
					},
					{
						"name": "finess",
						"type": "String"
					},
					{
						"name": "rs",
						"type": "String"
					},
					{
						"name": "adresse",
						"type": "String"
					},
					{
						"name": "cpl_loc",
						"type": "String"
					},
					{
						"name": "do_prel",
						"type": "String"
					},
					{
						"name": "do_antigenic",
						"type": "String"
					},
					{
						"name": "longitude",
						"type": "String"
					},
					{
						"name": "latitude",
						"type": "String"
					},
					{
						"name": "mod_prel",
						"type": "String"
					},
					{
						"name": "public",
						"type": "String"
					},
					{
						"name": "horaire",
						"type": "String"
					},
					{
						"name": "horaire_prio",
						"type": "String"
					},
					{
						"name": "check_rdv",
						"type": "String"
					},
					{
						"name": "tel_rdv",
						"type": "String"
					},
					{
						"name": "web_rdv",
						"type": "String"
					},
					{
						"name": "date_modif",
						"type": "String"
					}
				]
			},
			"dependsOn": [
				"[concat(variables('factoryId'), '/linkedServices/FileServer1')]"
			]
		},
		{
			"name": "[concat(parameters('factoryName'), '/Src3')]",
			"type": "Microsoft.DataFactory/factories/datasets",
			"apiVersion": "2018-06-01",
			"properties": {
				"linkedServiceName": {
					"referenceName": "FileServer1",
					"type": "LinkedServiceReference"
				},
				"annotations": [],
				"type": "DelimitedText",
				"typeProperties": {
					"location": {
						"type": "FileServerLocation",
						"fileName": "sp-variant-7j-fra-2021-03-18-17h20.csv"
					},
					"columnDelimiter": ";",
					"escapeChar": "\\",
					"firstRowAsHeader": true,
					"quoteChar": "\""
				},
				"schema": [
					{
						"name": "fra",
						"type": "String"
					},
					{
						"name": "semaine",
						"type": "String"
					},
					{
						"name": "cl_age90",
						"type": "String"
					},
					{
						"name": "Nb_tests_PCR_TA_crible",
						"type": "String"
					},
					{
						"name": "Prc_tests_PCR_TA_crible",
						"type": "String"
					},
					{
						"name": "Nb_susp_501Y_V1",
						"type": "String"
					},
					{
						"name": "Prc_susp_501Y_V1",
						"type": "String"
					},
					{
						"name": "Nb_susp_501Y_V2_3",
						"type": "String"
					},
					{
						"name": "Prc_susp_501Y_V2_3",
						"type": "String"
					},
					{
						"name": "Nb_susp_IND",
						"type": "String"
					},
					{
						"name": "Prc_susp_IND",
						"type": "String"
					},
					{
						"name": "Nb_susp_ABS",
						"type": "String"
					},
					{
						"name": "Prc_susp_ABS",
						"type": "String"
					}
				]
			},
			"dependsOn": [
				"[concat(variables('factoryId'), '/linkedServices/FileServer1')]"
			]
		},
		{
			"name": "[concat(parameters('factoryName'), '/Srccsv1')]",
			"type": "Microsoft.DataFactory/factories/datasets",
			"apiVersion": "2018-06-01",
			"properties": {
				"linkedServiceName": {
					"referenceName": "FileServer1",
					"type": "LinkedServiceReference"
				},
				"annotations": [],
				"type": "DelimitedText",
				"typeProperties": {
					"location": {
						"type": "FileServerLocation",
						"fileName": "data-1.csv"
					},
					"columnDelimiter": ",",
					"escapeChar": "\\",
					"firstRowAsHeader": true,
					"quoteChar": "\""
				},
				"schema": [
					{
						"name": "dateRep",
						"type": "String"
					},
					{
						"name": "day",
						"type": "String"
					},
					{
						"name": "month",
						"type": "String"
					},
					{
						"name": "year",
						"type": "String"
					},
					{
						"name": "cases",
						"type": "String"
					},
					{
						"name": "deaths",
						"type": "String"
					},
					{
						"name": "countriesAndTerritories",
						"type": "String"
					},
					{
						"name": "geoId",
						"type": "String"
					},
					{
						"name": "countryterritoryCode",
						"type": "String"
					},
					{
						"name": "popData2019",
						"type": "String"
					},
					{
						"name": "continentExp",
						"type": "String"
					},
					{
						"name": "Cumulative_number_for_14_days_of_COVID-19_cases_per_100000",
						"type": "String"
					}
				]
			},
			"dependsOn": [
				"[concat(variables('factoryId'), '/linkedServices/FileServer1')]"
			]
		},
		{
			"name": "[concat(parameters('factoryName'), '/Srccsv2')]",
			"type": "Microsoft.DataFactory/factories/datasets",
			"apiVersion": "2018-06-01",
			"properties": {
				"linkedServiceName": {
					"referenceName": "FileServer1",
					"type": "LinkedServiceReference"
				},
				"annotations": [],
				"type": "DelimitedText",
				"typeProperties": {
					"location": {
						"type": "FileServerLocation",
						"fileName": "data-2.csv"
					},
					"columnDelimiter": ",",
					"escapeChar": "\\",
					"firstRowAsHeader": true,
					"quoteChar": "\""
				},
				"schema": [
					{
						"name": "YearWeekISO",
						"type": "String"
					},
					{
						"name": "FirstDose",
						"type": "String"
					},
					{
						"name": "FirstDoseRefused",
						"type": "String"
					},
					{
						"name": "SecondDose",
						"type": "String"
					},
					{
						"name": "UnknownDose",
						"type": "String"
					},
					{
						"name": "NumberDosesReceived",
						"type": "String"
					},
					{
						"name": "Region",
						"type": "String"
					},
					{
						"name": "Population",
						"type": "String"
					},
					{
						"name": "ReportingCountry",
						"type": "String"
					},
					{
						"name": "TargetGroup",
						"type": "String"
					},
					{
						"name": "Vaccine",
						"type": "String"
					},
					{
						"name": "Denominator",
						"type": "String"
					}
				]
			},
			"dependsOn": [
				"[concat(variables('factoryId'), '/linkedServices/FileServer1')]"
			]
		},
		{
			"name": "[concat(parameters('factoryName'), '/Srccsv3')]",
			"type": "Microsoft.DataFactory/factories/datasets",
			"apiVersion": "2018-06-01",
			"properties": {
				"linkedServiceName": {
					"referenceName": "FileServer1",
					"type": "LinkedServiceReference"
				},
				"annotations": [],
				"type": "DelimitedText",
				"typeProperties": {
					"location": {
						"type": "FileServerLocation",
						"fileName": "data-3.csv"
					},
					"columnDelimiter": ",",
					"escapeChar": "\\",
					"firstRowAsHeader": true,
					"quoteChar": "\""
				},
				"schema": [
					{
						"name": "country",
						"type": "String"
					},
					{
						"name": "indicator",
						"type": "String"
					},
					{
						"name": "date",
						"type": "String"
					},
					{
						"name": "year_week",
						"type": "String"
					},
					{
						"name": "value",
						"type": "String"
					},
					{
						"name": "source",
						"type": "String"
					},
					{
						"name": "url",
						"type": "String"
					}
				]
			},
			"dependsOn": [
				"[concat(variables('factoryId'), '/linkedServices/FileServer1')]"
			]
		},
		{
			"name": "[concat(parameters('factoryName'), '/Srccsv4')]",
			"type": "Microsoft.DataFactory/factories/datasets",
			"apiVersion": "2018-06-01",
			"properties": {
				"linkedServiceName": {
					"referenceName": "FileServer1",
					"type": "LinkedServiceReference"
				},
				"annotations": [],
				"type": "DelimitedText",
				"typeProperties": {
					"location": {
						"type": "FileServerLocation",
						"fileName": "data-4.csv"
					},
					"columnDelimiter": ",",
					"escapeChar": "\\",
					"firstRowAsHeader": true,
					"quoteChar": "\""
				},
				"schema": [
					{
						"name": "country",
						"type": "String"
					},
					{
						"name": "country_code",
						"type": "String"
					},
					{
						"name": "year_week",
						"type": "String"
					},
					{
						"name": "level",
						"type": "String"
					},
					{
						"name": "region",
						"type": "String"
					},
					{
						"name": "region_name",
						"type": "String"
					},
					{
						"name": "new_cases",
						"type": "String"
					},
					{
						"name": "tests_done",
						"type": "String"
					},
					{
						"name": "population",
						"type": "String"
					},
					{
						"name": "testing_rate",
						"type": "String"
					},
					{
						"name": "positivity_rate",
						"type": "String"
					},
					{
						"name": "testing_data_source",
						"type": "String"
					}
				]
			},
			"dependsOn": [
				"[concat(variables('factoryId'), '/linkedServices/FileServer1')]"
			]
		},
		{
			"name": "[concat(parameters('factoryName'), '/Srccsv5')]",
			"type": "Microsoft.DataFactory/factories/datasets",
			"apiVersion": "2018-06-01",
			"properties": {
				"linkedServiceName": {
					"referenceName": "FileServer1",
					"type": "LinkedServiceReference"
				},
				"annotations": [],
				"type": "DelimitedText",
				"typeProperties": {
					"location": {
						"type": "FileServerLocation",
						"fileName": "data-5.csv"
					},
					"columnDelimiter": ",",
					"escapeChar": "\\",
					"firstRowAsHeader": true,
					"quoteChar": "\""
				},
				"schema": [
					{
						"name": "Country",
						"type": "String"
					},
					{
						"name": "Response_measure",
						"type": "String"
					},
					{
						"name": "date_start",
						"type": "String"
					},
					{
						"name": "date_end",
						"type": "String"
					}
				]
			},
			"dependsOn": [
				"[concat(variables('factoryId'), '/linkedServices/FileServer1')]"
			]
		}
	]
}